resotoworker/__init__.py
resotoworker/__main__.py
resotoworker/cleanup.py
resotoworker/collect.py
resotoworker/config.py
resotoworker/exceptions.py
resotoworker/pluginloader.py
resotoworker/resotocore.py
resotoworker/tag.py
resotoworker/utils.py
test/__init__.py
test/fakeconfig.py
test/test_args.py
test/test_collect.py
test/test_resotocore.py
test/test_utils.py
resotoworker-3.9.0.dist-info/METADATA
resotoworker-3.9.0.dist-info/WHEEL
resotoworker-3.9.0.dist-info/entry_points.txt
resotoworker-3.9.0.dist-info/top_level.txt
resotoworker-3.9.0.dist-info/RECORD
