Metadata-Version: 2.1
Name: resotoworker
Version: 3.9.0
Summary: Runs collector plugins and sends the result to resotocore.
Author: Some Engineering Inc.
License: AGPLv3
Project-URL: Documentation, https://resoto.com
Project-URL: Source, https://github.com/someengineering/resoto/tree/main/resotoworker
Classifier: Programming Language :: Python :: 3
Requires-Python: >=3.9
Requires-Dist: resotolib ==3.9.0
Requires-Dist: tenacity
Requires-Dist: CherryPy
